{"cameraMode":{"drawMode":0,"name":"Shaded","section":"Shading Mode"},"sceneLighting":false,"audioPlay":false,"sceneViewState":{"showFog":true,"showMaterialUpdate":false,"showSkybox":false,"showFlares":true,"showImageEffects":true,"showParticleSystems":true,"showVisualEffectGraphs":true,"m_FxEnabled":true},"in2DMode":false,"pivot":{"x":488.25,"y":274.5,"z":0.0},"rotation":{"x":-0.08416614681482315,"y":0.03197784349322319,"z":-0.0027023262809962036,"w":-0.9959332346916199},"size":560.1234741210938,"orthographic":false}